pymonad/__init__.py
pymonad/either.py
pymonad/io.py
pymonad/list.py
pymonad/maybe.py
pymonad/monad.py
pymonad/monoid.py
pymonad/promise.py
pymonad/reader.py
pymonad/state.py
pymonad/tools.py
pymonad/writer.py
pymonad/operators/__init__.py
pymonad/operators/either.py
pymonad/operators/io.py
pymonad/operators/list.py
pymonad/operators/maybe.py
pymonad/operators/operators.py
pymonad/operators/reader.py
pymonad/operators/state.py
pymonad/operators/writer.py
PyMonad-2.3.5.dist-info/LICENSE.rst
PyMonad-2.3.5.dist-info/METADATA
PyMonad-2.3.5.dist-info/WHEEL
PyMonad-2.3.5.dist-info/top_level.txt
PyMonad-2.3.5.dist-info/RECORD
