Metadata-Version: 2.1
Name: PyMonad
Version: 2.3.5
Summary: Data structures and utilities for monadic style functional programming.
Home-page: https://github.com/jasondelaat/pymonad
Author: Jason DeLaat
Author-email: jason.develops@gmail.com
License: BSD-3-Clause
Platform: UNKNOWN
Classifier: Intended Audience :: Developers
Classifier: License :: OSI Approved :: BSD License
Classifier: Operating System :: OS Independent
Classifier: Programming Language :: Python :: 3
Classifier: Topic :: Software Development
Classifier: Topic :: Software Development :: Libraries
Classifier: Topic :: Utilities
Requires-Python: >=3.7
